README.rst
setup.py
emulet/__init__.py
emulet/__main__.py
emulet/config_loader.py
emulet/funcs.py
emulet.egg-info/PKG-INFO
emulet.egg-info/SOURCES.txt
emulet.egg-info/dependency_links.txt
emulet.egg-info/not-zip-safe
emulet.egg-info/top_level.txt