Metadata-Version: 2.1
Name: emulet
Version: 1.3
Summary: TCP HoneyPot
Home-page: UNKNOWN
Author: vikas
Author-email: vikas4sharma4@gmail.com
License: MIT
Platform: UNKNOWN
